LICENSE
README.md
setup.py
src/chromedriver/__init__.py
src/chromedriver/chrome.py
src/chromedriver_plus.egg-info/PKG-INFO
src/chromedriver_plus.egg-info/SOURCES.txt
src/chromedriver_plus.egg-info/dependency_links.txt
src/chromedriver_plus.egg-info/requires.txt
src/chromedriver_plus.egg-info/top_level.txt