Metadata-Version: 2.1
Name: chromedriver-plus
Version: 0.0.7
Summary: Some of my favorite features
Home-page: https://github.com/nguyenvantat1182002/chromedriver_plus
Author: Tat Nguyen Van
Author-email: nguyenvantat7788@gmail.com
License: UNKNOWN
Platform: UNKNOWN
Classifier: Programming Language :: Python :: 3.7
Classifier: License :: OSI Approved :: MIT License
Requires-Python: >=3.7
License-File: LICENSE
